{
    "title": "A Bit of Adventure",
    "linkTitle": "a-bit-of-adventure",
    "img": "/static/projects/bit.jpg",
    "pageImgs": [
        "/static/projects/bit.jpg"
    ],
    "date": "Febuary 2024",
    "desc": "A short, quirky Bitsy adventure game about computer architecture and function",
    "authors": [
        "Alex Le",
        "Alina Vykliuk",
        "Erebus Oh",
        "Lily Davoren"
    ],
    "skills": [
        "Project Management",
        "Game Design",
        "Bitsy"
    ],
    "links": [
        "https://vykliuk.itch.io/a-bit-of-adventure"
    ]
}